PublicDataReader/__init__.py
PublicDataReader/data.py
PublicDataReader/PublicDataPortal/__init__.py
PublicDataReader/PublicDataPortal/kamco.py
PublicDataReader/PublicDataPortal/molit.py
PublicDataReader/PublicDataPortal/nts.py
PublicDataReader/PublicDataPortal/reb.py
PublicDataReader/PublicDataPortal/semas.py
PublicDataReader/Seoul/__init__.py
PublicDataReader/Seoul/transportation.py
PublicDataReader/config/__init__.py
PublicDataReader/config/info.py
PublicDataReader/ecos/__init__.py
PublicDataReader/ecos/ecos.py
PublicDataReader/fred/__init__.py
PublicDataReader/fred/fred.py
PublicDataReader/kbland/__init__.py
PublicDataReader/kbland/kbland.py
PublicDataReader/kosis/__init__.py
PublicDataReader/kosis/kosis.py
PublicDataReader/raw/code_bdong.json
PublicDataReader/raw/code_hdong.json
PublicDataReader/raw/code_hdong_bdong.json
PublicDataReader/raw/code_vworld.json
PublicDataReader/utils/__init__.py
PublicDataReader/utils/code.py
PublicDataReader/vworld/__init__.py
PublicDataReader/vworld/data.py
PublicDataReader-1.1.1.post2.dist-info/LICENSE
PublicDataReader-1.1.1.post2.dist-info/METADATA
PublicDataReader-1.1.1.post2.dist-info/WHEEL
PublicDataReader-1.1.1.post2.dist-info/top_level.txt
PublicDataReader-1.1.1.post2.dist-info/RECORD
