Metadata-Version: 2.1
Name: PublicDataReader
Version: 1.1.1.post2
Summary: Open Source Public Data Reader
Home-page: https://github.com/WooilJeong/PublicDataReader
Author: 정우일(Wooil Jeong)
Author-email: wooil@kakao.com
License: MIT
Platform: UNKNOWN
Classifier: Programming Language :: Python :: 3
Classifier: License :: OSI Approved :: MIT License
Classifier: Operating System :: OS Independent
Requires-Python: >=3.9
License-File: LICENSE
Requires-Dist: pandas==2.2.3
Requires-Dist: requests==2.32.3
Requires-Dist: xmltodict==0.14.2
Requires-Dist: beautifulsoup4==4.13.3
